chillin_server/__init__.py
chillin_server/config.py
chillin_server/components/__init__.py
chillin_server/components/core.py
chillin_server/components/game_handlers.py
chillin_server/components/network.py
chillin_server/components/protocol.py
chillin_server/default_certs/cert.pem
chillin_server/default_certs/key.pem
chillin_server/events/__init__.py
chillin_server/events/core.py
chillin_server/events/game_handlers.py
chillin_server/events/network.py
chillin_server/events/protocol.py
chillin_server/gui/__init__.py
chillin_server/gui/messages.py
chillin_server/gui/network.py
chillin_server/gui/parser.py
chillin_server/gui/protocol.py
chillin_server/gui/reference_manager.py
chillin_server/gui/replay_manager.py
chillin_server/gui/scene.py
chillin_server/gui/scene_actions.py
chillin_server/gui/screen.py
chillin_server/gui/tools.py
chillin_server/helpers/__init__.py
chillin_server/helpers/auth.py
chillin_server/helpers/datetiming.py
chillin_server/helpers/logger.py
chillin_server/helpers/master_server.py
chillin_server/helpers/messages.py
chillin_server/helpers/parser.py
chillin_server/helpers/singleton.py
chillin_server-2.3.0.dist-info/LICENSE
chillin_server-2.3.0.dist-info/METADATA
chillin_server-2.3.0.dist-info/WHEEL
chillin_server-2.3.0.dist-info/top_level.txt
chillin_server-2.3.0.dist-info/RECORD
