Metadata-Version: 2.1
Name: chillin-server
Version: 2.3.0
Summary: Chillin AI Game Framework (Python Server)
Home-page: https://github.com/koala-team/Chillin-PyServer
Author: Koala
Author-email: mdan.hagh@gmail.com
License: AGPL License, Version 3.0
Keywords: ai game framework chillin
Platform: UNKNOWN
Classifier: Environment :: Console
Classifier: License :: OSI Approved :: GNU Affero General Public License v3
Classifier: Intended Audience :: Developers
Classifier: Operating System :: OS Independent
Classifier: Programming Language :: Python :: 2.7
Classifier: Programming Language :: Python :: 3.5
Classifier: Topic :: Software Development :: Libraries :: Application Frameworks
Requires-Dist: circuits (==3.2)
Requires-Dist: pydblite (==3.0.4)
Requires-Dist: configparser (==3.5.0)
Requires-Dist: enum34 (==1.1.6)
Provides-Extra: dev
Requires-Dist: koala-serializer ; extra == 'dev'
